mealey.v
module mealey(x,reset,clk,y);
	input x,reset,clk;
	output reg y;
	parameter A=0, B=1, C=2, D=3, E=4;
	reg [2:0] ps,ns;
	always@(posedge clk, posedge reset)
	begin
		if(reset)
			ps <= A;
		else
			ps <= ns;
	end

	always@(ps,x)
	begin
		case(ps)
			A:	begin
					y = 0;
					ns = x ? B : A;
				end
			B:	begin
					y=0;
					ns = x ? B : C;
				end
			C:	begin
					y=0;
					ns = x ? D : A;
				end
			D:	begin
					y = x ? 0 : 1;
					ns = x ? B: E;
				end
			E:	begin
					y=0;
					ns = x ? D : A;
				end
			default: ps=A;
		endcase
	end
endmodule

module TestMileyMachine;
	reg in,CLK, RESET;
	wire Out;
	mealey dut(.x(in), .clk(CLK), .reset(RESET), .y(Out));
	initial
	begin
		$dumpfile("mealey.vcd"); $dumpvars(0,TestMileyMachine);
		$display("\nThe mealey Machine to check the sequence 1010");
	end
	always #5 CLK=~CLK;
	initial
	begin
		$monitor($time, "\tRESET=%b\tCLK=%b\tINP=%b\tOUT=%b",RESET,CLK,in,Out);
		RESET=1; CLK=0;
		#12 RESET=0;
		 #8 in=1; #10 in=0; #10 in=1; #10 in=0;
		#10 in=0; #10 in=1; #10 in=0; #10 in=1;
		#10 in=0; #10 in=1; #10 in=0; #10 in=0;
		#10 $finish;
	end
endmodule

mealey.vcd
$date
	Wed Nov 28 10:25:35 2018
$end
$version
	Icarus Verilog
$end
$timescale
	1s
$end
$scope module TestMileyMachine $end
$var wire 1 ! Out $end
$var reg 1 " CLK $end
$var reg 1 # RESET $end
$var reg 1 $ in $end
$scope module dut $end
$var wire 1 % clk $end
$var wire 1 & reset $end
$var wire 1 ' x $end
$var reg 3 ( ns [2:0] $end
$var reg 3 ) ps [2:0] $end
$var reg 1 * y $end
$upscope $end
$upscope $end
$enddefinitions $end
#0
$dumpvars
0*
b0 )
b0x (
x'
1&
0%
x$
1#
0"
0!
$end
#5
1"
1%
#10
0"
0%
#12
0#
0&
#15
b0 )
1"
1%
#20
b1 (
0"
0%
1$
1'
#25
b1 )
1"
1%
#30
b10 (
0"
0%
0$
0'
#35
b0 (
b10 )
1"
1%
#40
b11 (
0"
0%
1$
1'
#45
b1 (
b11 )
1"
1%
#50
b100 (
1*
1!
0"
0%
0$
0'
#55
b0 (
0*
0!
b100 )
1"
1%
#60
0"
0%
#65
b0 )
1"
1%
#70
b1 (
0"
0%
1$
1'
#75
b1 )
1"
1%
#80
b10 (
0"
0%
0$
0'
#85
b0 (
b10 )
1"
1%
#90
b11 (
0"
0%
1$
1'
#95
b1 (
b11 )
1"
1%
#100
b100 (
1*
1!
0"
0%
0$
0'
#105
b0 (
0*
0!
b100 )
1"
1%
#110
b11 (
0"
0%
1$
1'
#115
b1 (
b11 )
1"
1%
#120
b100 (
1*
1!
0"
0%
0$
0'
#125
b0 (
0*
0!
b100 )
1"
1%
#130
0"
0%
#135
b0 )
1"
1%
